xmlmerge/__init__.py
xmlmerge/xmlmerge.py
xmlmerge-1.1.4.dist-info/LICENSE
xmlmerge-1.1.4.dist-info/METADATA
xmlmerge-1.1.4.dist-info/WHEEL
xmlmerge-1.1.4.dist-info/entry_points.txt
xmlmerge-1.1.4.dist-info/top_level.txt
xmlmerge-1.1.4.dist-info/RECORD
