Metadata-Version: 2.1
Name: xmlmerge
Version: 1.1.4
Summary: XMLMerge is simple tool to merge multiple xml files.
Home-page: https://github.com/kirankotari/xmlmerge.git
Author: Kiran Kumar Kotari
Author-email: kirankotari@live.com
License: UNKNOWN
Keywords: xml xmlmerge
Platform: UNKNOWN
Classifier: Development Status :: 3 - Alpha
Classifier: Intended Audience :: Developers
Classifier: Topic :: Software Development :: Build Tools
Classifier: License :: OSI Approved :: MIT License
Classifier: Operating System :: OS Independent
Classifier: Programming Language :: Python :: 2.7
Classifier: Programming Language :: Python :: 3.5
Classifier: Programming Language :: Python :: 3.6
Classifier: Programming Language :: Python :: 3.7
License-File: LICENSE
Requires-Dist: pandas (==1.3.4)
